LICENSE.txt
MANIFEST.in
README.rst
setup.cfg
setup.py
XsCrypto/AES.py
XsCrypto/Affine.py
XsCrypto/Des.py
XsCrypto/Morse.py
XsCrypto/RSA.py
XsCrypto/RSA_Common_Modulus_Attack.py
XsCrypto/RSA_Wiener_Arithmetic.py
XsCrypto/RSA_Wiener_Attack.py
XsCrypto/RSA_Wiener_ContinuedFractions.py
XsCrypto/Strings.py
XsCrypto/Substitution.py
XsCrypto/Vigenere.py
XsCrypto/__init__.py
XsCrypto/base36.py
XsCrypto/jinzhi.py
XsCrypto/test_data.py
XsCrypto/zhanzhuanxc.py
XsCrypto.egg-info/PKG-INFO
XsCrypto.egg-info/SOURCES.txt
XsCrypto.egg-info/dependency_links.txt
XsCrypto.egg-info/top_level.txt