Metadata-Version: 1.1
Name: XsCrypto
Version: 2.1.0
Summary: A CTFCrypto Tools project
Home-page: https://github.com/ByStudent666/XsCrypto
Author: ByStudent
Author-email: bystudent@163.com
License: MIT
Keywords: XsCrypto setuptools development
Platform: UNKNOWN
Classifier: Development Status :: 3 - Alpha
Classifier: Intended Audience :: Developers
Classifier: Topic :: Software Development :: Build Tools
Classifier: License :: OSI Approved :: MIT License
Classifier: Programming Language :: Python :: 2.7
